nodice/__main__.py
nodice/cli.py
nodice/diceware.py
nodice/wordlists/bip_0039.txt
nodice/wordlists/eff_large_wordlist.txt
nodice/wordlists/eff_short_wordlist_1.txt
nodice/wordlists/eff_short_wordlist_2_0.txt
nodice_cli-0.1.0.dist-info/LICENSE
nodice_cli-0.1.0.dist-info/METADATA
nodice_cli-0.1.0.dist-info/WHEEL
nodice_cli-0.1.0.dist-info/entry_points.txt
nodice_cli-0.1.0.dist-info/top_level.txt
nodice_cli-0.1.0.dist-info/RECORD
