Metadata-Version: 2.1
Name: nodice-cli
Version: 0.1.0
Summary: A simple diceware generator with no dependencies.
Author: avnigo
License: MIT License
Project-URL: Homepage, https://github.com/avnigo/nodice-cli
Project-URL: Bug Tracker, https://github.com/avnigo/nodice-cli/issues
Classifier: Programming Language :: Python :: 3
Classifier: License :: OSI Approved :: MIT License
Classifier: Operating System :: OS Independent
Classifier: Topic :: Security
Classifier: Topic :: Utilities
Requires-Python: >=3.8
License-File: LICENSE
